{
  "hash": "0cd36d17c7b4a49b77b4d76a38c114d3",
  "result": {
    "engine": "knitr",
    "markdown": "---\ntitle: \"In Class Exercise 3\"\nauthor: \"Santhya Selvan\"\n---\n\n\nWhen we need to use packages that have been retired, we can download them from archives. In this example below I am downloading fro posit package manager. The date indicates the version of the package.\n\n\n::: {.cell}\n\n```{.r .cell-code}\ninstall.packages (\"maptools\",\n                  repos = \"https://packagemanager.posit.co/cran/2023-10-13\")\n```\n:::\n",
    "supporting": [],
    "filters": [
      "rmarkdown/pagebreak.lua"
    ],
    "includes": {},
    "engineDependencies": {},
    "preserve": {},
    "postProcess": true
  }
}